abspy/__init__.py
abspy/complex.py
abspy/graph.py
abspy/logger.py
abspy/primitive.py
abspy/version.py
abspy-0.3.0.dist-info/licenses/LICENSE
abspy-0.3.0.dist-info/METADATA
abspy-0.3.0.dist-info/WHEEL
abspy-0.3.0.dist-info/top_level.txt
abspy-0.3.0.dist-info/RECORD
