Metadata-Version: 2.4
Name: abspy
Version: 0.3.0
Summary: A Python tool for 3D adaptive binary space partitioning and beyond
Home-page: https://github.com/chenzhaiyu/abspy
Author: Zhaiyu Chen
Author-email: zhaiyu.chen@outlook.com
License: 'MIT'
Project-URL: Bug Tracker, https://github.com/chenzhaiyu/abspy/issues
Classifier: Programming Language :: Python :: 3
Classifier: License :: OSI Approved :: MIT License
Classifier: Operating System :: OS Independent
Requires-Python: >=3.6
License-File: LICENSE
Dynamic: license-file
